bigeye_airflow/__init__.py
bigeye_airflow/airflow_datawatch_client.py
bigeye_airflow/airflow_ext/__init__.py
bigeye_airflow/airflow_ext/bigeye_airflow_httphook.py
bigeye_airflow/aws/__init__.py
bigeye_airflow/aws/s3_utils.py
bigeye_airflow/bigeye_requests/__init__.py
bigeye_airflow/bigeye_requests/catalog_requests.py
bigeye_airflow/bigeye_requests/http_hook.py
bigeye_airflow/bigeye_requests/metric_requests.py
bigeye_airflow/functions/__init__.py
bigeye_airflow/models/__init__.py
bigeye_airflow/models/configurations.py
bigeye_airflow/operators/__init__.py
bigeye_airflow/operators/bigeye_dbt_operator.py
bigeye_airflow/operators/client_extensible_operator.py
bigeye_airflow/operators/create_custom_rules_operator.py
bigeye_airflow/operators/create_delta_operator.py
bigeye_airflow/operators/create_metric_operator.py
bigeye_airflow/operators/create_sla_operator.py
bigeye_airflow/operators/lineage_plus_operator.py
bigeye_airflow/operators/run_custom_rules_operator.py
bigeye_airflow/operators/run_deltas_operator.py
bigeye_airflow/operators/run_metrics_operator.py
bigeye_airflow-0.2.0.dist-info/LICENSE
bigeye_airflow-0.2.0.dist-info/METADATA
bigeye_airflow-0.2.0.dist-info/WHEEL
bigeye_airflow-0.2.0.dist-info/RECORD
