Metadata-Version: 2.1
Name: bigeye-airflow
Version: 0.2.0
Summary: Bigeye Airflow Library supports Airflow versions >=2.6.3 and offers custom operators for interacting with your bigeye workspace.
Home-page: https://docs.bigeye.com/docs
License: Proprietary
Author: Bigeye
Author-email: support@bigeye.com
Requires-Python: >=3.11.0,<4.0.0
Classifier: License :: Other/Proprietary License
Classifier: Programming Language :: Python :: 3
Classifier: Programming Language :: Python :: 3.11
Classifier: Programming Language :: Python :: 3.12
Requires-Dist: Flask-OpenID (>=1.3.0,<2.0.0)
Requires-Dist: apache-airflow (>=2.6.3,<=2.11)
Requires-Dist: bigeye-sdk (>=0.8.0,<0.9.0)
